payflare/Payflare.py
payflare/__init__.py
payflare-0.0.5.dist-info/LICENSE.txt
payflare-0.0.5.dist-info/METADATA
payflare-0.0.5.dist-info/WHEEL
payflare-0.0.5.dist-info/top_level.txt
payflare-0.0.5.dist-info/RECORD
