Metadata-Version: 2.1
Name: payflare
Version: 0.0.5
Summary: Payflare.io Python Client Library
Home-page: https://github.com/payflare/paylfare.py
Author: Payflare
License: MIT
License-File: LICENSE.txt
